anon/__init__.py
anon/base.py
anon/compat.py
anon/utils.py
tests/__init__.py
tests/compat.py
tests/models.py
tests/settings.py
tests/test_base.py
tests/test_compat.py
tests/test_utils.py
django_anon-0.3.2.dist-info/LICENSE
django_anon-0.3.2.dist-info/METADATA
django_anon-0.3.2.dist-info/WHEEL
django_anon-0.3.2.dist-info/top_level.txt
django_anon-0.3.2.dist-info/RECORD
