Metadata-Version: 2.1
Name: django-anon
Version: 0.3.2
Summary: Anonymize production data so it can be safely used in not-so-safe environments
Home-page: https://github.com/Tesorio/django-anon
Author: Tesorio
Author-email: hello@tesorio.com
License: MIT
Platform: any
Classifier: Development Status :: 5 - Production/Stable
Classifier: Intended Audience :: Developers
Classifier: License :: OSI Approved :: MIT License
Classifier: Operating System :: OS Independent
Classifier: Framework :: Django
Classifier: Programming Language :: Python
Classifier: Programming Language :: Python :: 2
Classifier: Programming Language :: Python :: 3
Requires-Dist: django-bulk-update
Requires-Dist: django-chunkator (<2)
